README.rst
setup.py
ssshelf/__init__.py
ssshelf/collections.py
ssshelf/items.py
ssshelf/keys.py
ssshelf/managers.py
ssshelf/utils.py
ssshelf.egg-info/PKG-INFO
ssshelf.egg-info/SOURCES.txt
ssshelf.egg-info/dependency_links.txt
ssshelf.egg-info/not-zip-safe
ssshelf.egg-info/requires.txt
ssshelf.egg-info/top_level.txt
ssshelf/storages/__init__.py
ssshelf/storages/cached.py
ssshelf/storages/inmemory.py
ssshelf/storages/lsm.py
ssshelf/storages/proxy.py
ssshelf/storages/redis.py
ssshelf/storages/s3.py